odoo/addons/website_membership_random_order/README.rst
odoo/addons/website_membership_random_order/__init__.py
odoo/addons/website_membership_random_order/__manifest__.py
odoo/addons/website_membership_random_order/controllers/__init__.py
odoo/addons/website_membership_random_order/controllers/main.py
odoo/addons/website_membership_random_order/i18n/es.po
odoo/addons/website_membership_random_order/i18n/it.po
odoo/addons/website_membership_random_order/i18n/website_membership_random_order.pot
odoo/addons/website_membership_random_order/models/__init__.py
odoo/addons/website_membership_random_order/models/membership_line.py
odoo/addons/website_membership_random_order/readme/CONTRIBUTORS.rst
odoo/addons/website_membership_random_order/readme/DESCRIPTION.rst
odoo/addons/website_membership_random_order/readme/ROADMAP.rst
odoo/addons/website_membership_random_order/static/description/icon.png
odoo/addons/website_membership_random_order/static/description/index.html
odoo/addons/website_membership_random_order/templates/website_membership_templates.xml
odoo14_addon_website_membership_random_order-14.0.1.0.1.dev7.dist-info/METADATA
odoo14_addon_website_membership_random_order-14.0.1.0.1.dev7.dist-info/WHEEL
odoo14_addon_website_membership_random_order-14.0.1.0.1.dev7.dist-info/top_level.txt
odoo14_addon_website_membership_random_order-14.0.1.0.1.dev7.dist-info/RECORD
